odoo/addons/account_commission_oca/README.rst
odoo/addons/account_commission_oca/__init__.py
odoo/addons/account_commission_oca/__manifest__.py
odoo/addons/account_commission_oca/data/menuitem_data.xml
odoo/addons/account_commission_oca/i18n/account_commission_oca.pot
odoo/addons/account_commission_oca/i18n/es.po
odoo/addons/account_commission_oca/i18n/hr.po
odoo/addons/account_commission_oca/i18n/it.po
odoo/addons/account_commission_oca/i18n/ja.po
odoo/addons/account_commission_oca/i18n/pt.po
odoo/addons/account_commission_oca/i18n/pt_BR.po
odoo/addons/account_commission_oca/i18n/tr.po
odoo/addons/account_commission_oca/models/__init__.py
odoo/addons/account_commission_oca/models/account_move.py
odoo/addons/account_commission_oca/models/commission.py
odoo/addons/account_commission_oca/models/commission_settlement.py
odoo/addons/account_commission_oca/readme/CONFIGURE.md
odoo/addons/account_commission_oca/readme/CONTRIBUTORS.md
odoo/addons/account_commission_oca/readme/DESCRIPTION.md
odoo/addons/account_commission_oca/readme/USAGE.md
odoo/addons/account_commission_oca/report/__init__.py
odoo/addons/account_commission_oca/report/commission_analysis.py
odoo/addons/account_commission_oca/report/commission_analysis_view.xml
odoo/addons/account_commission_oca/security/account_commission_security.xml
odoo/addons/account_commission_oca/security/ir.model.access.csv
odoo/addons/account_commission_oca/static/description/icon.png
odoo/addons/account_commission_oca/static/description/icon.svg
odoo/addons/account_commission_oca/static/description/index.html
odoo/addons/account_commission_oca/tests/__init__.py
odoo/addons/account_commission_oca/tests/test_account_commission.py
odoo/addons/account_commission_oca/views/account_move_views.xml
odoo/addons/account_commission_oca/views/commission_settlement_views.xml
odoo/addons/account_commission_oca/views/commission_views.xml
odoo/addons/account_commission_oca/views/report_settlement_templates.xml
odoo_addon_account_commission_oca-19.0.1.0.0.2.dist-info/METADATA
odoo_addon_account_commission_oca-19.0.1.0.0.2.dist-info/WHEEL
odoo_addon_account_commission_oca-19.0.1.0.0.2.dist-info/top_level.txt
odoo_addon_account_commission_oca-19.0.1.0.0.2.dist-info/RECORD
