Metadata-Version: 2.1
Name: odoo-addon-account_commission_oca
Version: 19.0.1.0.0.2
Requires-Dist: odoo-addon-commission_oca==19.0.*
Requires-Dist: odoo==19.0.*
Summary: Account commissions OCA
Home-page: https://github.com/OCA/commission
License: AGPL-3
Author: Tecnativa, Odoo Community Association (OCA)
Author-email: support@odoo-community.org
Classifier: Programming Language :: Python
Classifier: Framework :: Odoo
Classifier: Framework :: Odoo :: 19.0
Classifier: License :: OSI Approved :: GNU Affero General Public License v3
